README.rst
setup.py
django_sluggable.egg-info/PKG-INFO
django_sluggable.egg-info/SOURCES.txt
django_sluggable.egg-info/dependency_links.txt
django_sluggable.egg-info/not-zip-safe
django_sluggable.egg-info/top_level.txt
sluggable/__init__.py
sluggable/fields.py
sluggable/models.py
sluggable/settings.py
sluggable/utils.py
sluggable/views.py
sluggable/tests/__init__.py
sluggable/tests/models.py
sluggable/tests/settings.py
sluggable/tests/tests.py
sluggable/tests/migrations/0001_initial.py
sluggable/tests/migrations/__init__.py