Metadata-Version: 1.1
Name: django-sluggable
Version: 0.7.0
Summary: Slug your multiple models and manage redirections
Home-page: http://github.com/thoas/django-sluggable
Author: Florent Messa
Author-email: florent.messa@gmail.com
License: UNKNOWN
Platform: UNKNOWN
Classifier: Environment :: Web Environment
Classifier: Intended Audience :: Developers
Classifier: License :: OSI Approved :: MIT License
Classifier: Operating System :: OS Independent
Classifier: Programming Language :: Python
Classifier: Programming Language :: Python :: 3
Classifier: Topic :: Utilities
